dj_pony/django_docker_test_dbs/__init__.py
dj_pony/django_docker_test_dbs/apps.py
dj_pony/django_docker_test_dbs/docker_db_in_memory.py
dj_pony/django_docker_test_dbs/models.py
dj_pony/django_docker_test_dbs/static/css/dj_pony_docker_test_dbs.css
dj_pony/django_docker_test_dbs/static/img/.gitignore
dj_pony/django_docker_test_dbs/static/js/dj_pony_docker_test_dbs.js
dj_pony/django_docker_test_dbs/templates/dj_pony_docker_test_dbs/base.html
dj_pony/django_docker_test_dbs/urls.py
dj_pony/django_docker_test_dbs/views.py
dj_pony.django_docker_test_dbs-0.2.0.dist-info/LICENSE
dj_pony.django_docker_test_dbs-0.2.0.dist-info/WHEEL
dj_pony.django_docker_test_dbs-0.2.0.dist-info/METADATA
dj_pony.django_docker_test_dbs-0.2.0.dist-info/RECORD
