Metadata-Version: 2.1
Name: dj-pony.django-docker-test-dbs
Version: 0.2.0
Summary: 
Author: Samuel Bishop
Author-email: sam@techdragon.io
Requires-Python: >=3.6,<4.0
Classifier: Programming Language :: Python :: 3
Classifier: Programming Language :: Python :: 3.6
Classifier: Programming Language :: Python :: 3.7
Requires-Dist: docker (>=4.0,<5.0)
